saudi_id_validator.py
saudi_id_validator-1.0.7.dist-info/LICENSE
saudi_id_validator-1.0.7.dist-info/METADATA
saudi_id_validator-1.0.7.dist-info/WHEEL
saudi_id_validator-1.0.7.dist-info/top_level.txt
saudi_id_validator-1.0.7.dist-info/RECORD
