Metadata-Version: 2.1
Name: saudi-id-validator
Version: 1.0.7
Summary: Validate ID numbers of Saudi Arabian identity cards
Home-page: UNKNOWN
Author: Mohd Alshehri
Author-email: 
License: MIT
Keywords: saudi government validator identity number
Platform: UNKNOWN
Classifier: Development Status :: 7 - Inactive
Requires-Python: >=3.5
License-File: LICENSE
